{
  "id": "a3551911-1852-468a-8b81-1a5fd5896cf1",
  "prevId": "f8a2aba7-93eb-4f3a-8a2a-c9503a99360d",
  "version": "7",
  "dialect": "postgresql",
  "tables": {
    "public.academic_commitments": {
      "name": "academic_commitments",
      "schema": "",
      "columns": {
        "id": {
          "name": "id",
          "type": "serial",
          "primaryKey": true,
          "notNull": true
        },
        "user_id": {
          "name": "user_id",
          "type": "integer",
          "primaryKey": false,
          "notNull": false
        },
        "title": {
          "name": "title",
          "type": "text",
          "primaryKey": false,
          "notNull": true
        },
        "type": {
          "name": "type",
          "type": "text",
          "primaryKey": false,
          "notNull": true
        },
        "course_id": {
          "name": "course_id",
          "type": "integer",
          "primaryKey": false,
          "notNull": false
        },
        "description": {
          "name": "description",
          "type": "text",
          "primaryKey": false,
          "notNull": false
        },
        "venue": {
          "name": "venue",
          "type": "text",
          "primaryKey": false,
          "notNull": false
        },
        "topic": {
          "name": "topic",
          "type": "text",
          "primaryKey": false,
          "notNull": false
        },
        "start_time": {
          "name": "start_time",
          "type": "text",
          "primaryKey": false,
          "notNull": true
        },
        "end_time": {
          "name": "end_time",
          "type": "text",
          "primaryKey": false,
          "notNull": true
        },
        "day_of_week": {
          "name": "day_of_week",
          "type": "integer",
          "primaryKey": false,
          "notNull": false
        },
        "specific_date": {
          "name": "specific_date",
          "type": "date",
          "primaryKey": false,
          "notNull": false
        },
        "is_recurring": {
          "name": "is_recurring",
          "type": "boolean",
          "primaryKey": false,
          "notNull": false,
          "default": false
        },
        "priority": {
          "name": "priority",
          "type": "integer",
          "primaryKey": false,
          "notNull": false,
          "default": 1
        },
        "created_at": {
          "name": "created_at",
          "type": "text",
          "primaryKey": false,
          "notNull": false,
          "default": "CURRENT_TIMESTAMP"
        }
      },
      "indexes": {
        "commitments_day_of_week_idx": {
          "name": "commitments_day_of_week_idx",
          "columns": [
            {
              "expression": "day_of_week",
              "isExpression": false,
              "asc": true,
              "nulls": "last"
            }
          ],
          "isUnique": false,
          "concurrently": false,
          "method": "btree",
          "with": {}
        },
        "commitments_specific_date_idx": {
          "name": "commitments_specific_date_idx",
          "columns": [
            {
              "expression": "specific_date",
              "isExpression": false,
              "asc": true,
              "nulls": "last"
            }
          ],
          "isUnique": false,
          "concurrently": false,
          "method": "btree",
          "with": {}
        },
        "commitments_type_idx": {
          "name": "commitments_type_idx",
          "columns": [
            {
              "expression": "type",
              "isExpression": false,
              "asc": true,
              "nulls": "last"
            }
          ],
          "isUnique": false,
          "concurrently": false,
          "method": "btree",
          "with": {}
        },
        "commitments_user_id_idx": {
          "name": "commitments_user_id_idx",
          "columns": [
            {
              "expression": "user_id",
              "isExpression": false,
              "asc": true,
              "nulls": "last"
            }
          ],
          "isUnique": false,
          "concurrently": false,
          "method": "btree",
          "with": {}
        }
      },
      "foreignKeys": {
        "academic_commitments_user_id_users_id_fk": {
          "name": "academic_commitments_user_id_users_id_fk",
          "tableFrom": "academic_commitments",
          "tableTo": "users",
          "columnsFrom": [
            "user_id"
          ],
          "columnsTo": [
            "id"
          ],
          "onDelete": "no action",
          "onUpdate": "no action"
        },
        "academic_commitments_course_id_courses_id_fk": {
          "name": "academic_commitments_course_id_courses_id_fk",
          "tableFrom": "academic_commitments",
          "tableTo": "courses",
          "columnsFrom": [
            "course_id"
          ],
          "columnsTo": [
            "id"
          ],
          "onDelete": "no action",
          "onUpdate": "no action"
        }
      },
      "compositePrimaryKeys": {},
      "uniqueConstraints": {},
      "policies": {},
      "checkConstraints": {},
      "isRLSEnabled": false
    },
    "public.activity_library": {
      "name": "activity_library",
      "schema": "",
      "columns": {
        "id": {
          "name": "id",
          "type": "serial",
          "primaryKey": true,
          "notNull": true
        },
        "user_id": {
          "name": "user_id",
          "type": "integer",
          "primaryKey": false,
          "notNull": false
        },
        "name": {
          "name": "name",
          "type": "text",
          "primaryKey": false,
          "notNull": true
        },
        "category": {
          "name": "category",
          "type": "text",
          "primaryKey": false,
          "notNull": true
        },
        "default_duration": {
          "name": "default_duration",
          "type": "integer",
          "primaryKey": false,
          "notNull": false,
          "default": 30
        },
        "is_default": {
          "name": "is_default",
          "type": "boolean",
          "primaryKey": false,
          "notNull": false,
          "default": false
        },
        "is_active": {
          "name": "is_active",
          "type": "boolean",
          "primaryKey": false,
          "notNull": false,
          "default": true
        },
        "preferred_time": {
          "name": "preferred_time",
          "type": "text",
          "primaryKey": false,
          "notNull": false
        },
        "usage_count": {
          "name": "usage_count",
          "type": "integer",
          "primaryKey": false,
          "notNull": false,
          "default": 0
        },
        "last_used_at": {
          "name": "last_used_at",
          "type": "text",
          "primaryKey": false,
          "notNull": false
        },
        "created_at": {
          "name": "created_at",
          "type": "text",
          "primaryKey": false,
          "notNull": false,
          "default": "CURRENT_TIMESTAMP"
        }
      },
      "indexes": {
        "activity_library_user_id_idx": {
          "name": "activity_library_user_id_idx",
          "columns": [
            {
              "expression": "user_id",
              "isExpression": false,
              "asc": true,
              "nulls": "last"
            }
          ],
          "isUnique": false,
          "concurrently": false,
          "method": "btree",
          "with": {}
        }
      },
      "foreignKeys": {
        "activity_library_user_id_users_id_fk": {
          "name": "activity_library_user_id_users_id_fk",
          "tableFrom": "activity_library",
          "tableTo": "users",
          "columnsFrom": [
            "user_id"
          ],
          "columnsTo": [
            "id"
          ],
          "onDelete": "no action",
          "onUpdate": "no action"
        }
      },
      "compositePrimaryKeys": {},
      "uniqueConstraints": {},
      "policies": {},
      "checkConstraints": {},
      "isRLSEnabled": false
    },
    "public.books": {
      "name": "books",
      "schema": "",
      "columns": {
        "id": {
          "name": "id",
          "type": "serial",
          "primaryKey": true,
          "notNull": true
        },
        "user_id": {
          "name": "user_id",
          "type": "integer",
          "primaryKey": false,
          "notNull": false
        },
        "title": {
          "name": "title",
          "type": "text",
          "primaryKey": false,
          "notNull": true
        },
        "author": {
          "name": "author",
          "type": "text",
          "primaryKey": false,
          "notNull": false
        },
        "status": {
          "name": "status",
          "type": "text",
          "primaryKey": false,
          "notNull": false,
          "default": "'to_read'"
        },
        "notes": {
          "name": "notes",
          "type": "text",
          "primaryKey": false,
          "notNull": false
        },
        "time_category": {
          "name": "time_category",
          "type": "text",
          "primaryKey": false,
          "notNull": false,
          "default": "'free_time'"
        },
        "current_page": {
          "name": "current_page",
          "type": "integer",
          "primaryKey": false,
          "notNull": false
        },
        "total_pages": {
          "name": "total_pages",
          "type": "integer",
          "primaryKey": false,
          "notNull": false
        },
        "total_chapters": {
          "name": "total_chapters",
          "type": "integer",
          "primaryKey": false,
          "notNull": false
        },
        "current_chapter": {
          "name": "current_chapter",
          "type": "integer",
          "primaryKey": false,
          "notNull": false,
          "default": 0
        },
        "created_at": {
          "name": "created_at",
          "type": "text",
          "primaryKey": false,
          "notNull": false,
          "default": "CURRENT_TIMESTAMP"
        },
        "completed_at": {
          "name": "completed_at",
          "type": "text",
          "primaryKey": false,
          "notNull": false
        }
      },
      "indexes": {
        "books_user_id_idx": {
          "name": "books_user_id_idx",
          "columns": [
            {
              "expression": "user_id",
              "isExpression": false,
              "asc": true,
              "nulls": "last"
            }
          ],
          "isUnique": false,
          "concurrently": false,
          "method": "btree",
          "with": {}
        }
      },
      "foreignKeys": {
        "books_user_id_users_id_fk": {
          "name": "books_user_id_users_id_fk",
          "tableFrom": "books",
          "tableTo": "users",
          "columnsFrom": [
            "user_id"
          ],
          "columnsTo": [
            "id"
          ],
          "onDelete": "no action",
          "onUpdate": "no action"
        }
      },
      "compositePrimaryKeys": {},
      "uniqueConstraints": {},
      "policies": {},
      "checkConstraints": {},
      "isRLSEnabled": false
    },
    "public.chapter_completions": {
      "name": "chapter_completions",
      "schema": "",
      "columns": {
        "id": {
          "name": "id",
          "type": "serial",
          "primaryKey": true,
          "notNull": true
        },
        "book_id": {
          "name": "book_id",
          "type": "integer",
          "primaryKey": false,
          "notNull": true
        },
        "chapter_number": {
          "name": "chapter_number",
          "type": "integer",
          "primaryKey": false,
          "notNull": true
        },
        "completed_at": {
          "name": "completed_at",
          "type": "date",
          "primaryKey": false,
          "notNull": true
        }
      },
      "indexes": {
        "chapter_completions_book_date_idx": {
          "name": "chapter_completions_book_date_idx",
          "columns": [
            {
              "expression": "book_id",
              "isExpression": false,
              "asc": true,
              "nulls": "last"
            },
            {
              "expression": "completed_at",
              "isExpression": false,
              "asc": true,
              "nulls": "last"
            }
          ],
          "isUnique": false,
          "concurrently": false,
          "method": "btree",
          "with": {}
        },
        "chapter_completions_date_idx": {
          "name": "chapter_completions_date_idx",
          "columns": [
            {
              "expression": "completed_at",
              "isExpression": false,
              "asc": true,
              "nulls": "last"
            }
          ],
          "isUnique": false,
          "concurrently": false,
          "method": "btree",
          "with": {}
        }
      },
      "foreignKeys": {
        "chapter_completions_book_id_books_id_fk": {
          "name": "chapter_completions_book_id_books_id_fk",
          "tableFrom": "chapter_completions",
          "tableTo": "books",
          "columnsFrom": [
            "book_id"
          ],
          "columnsTo": [
            "id"
          ],
          "onDelete": "no action",
          "onUpdate": "no action"
        }
      },
      "compositePrimaryKeys": {},
      "uniqueConstraints": {},
      "policies": {},
      "checkConstraints": {},
      "isRLSEnabled": false
    },
    "public.concept_tracking": {
      "name": "concept_tracking",
      "schema": "",
      "columns": {
        "id": {
          "name": "id",
          "type": "serial",
          "primaryKey": true,
          "notNull": true
        },
        "user_id": {
          "name": "user_id",
          "type": "integer",
          "primaryKey": false,
          "notNull": false
        },
        "course_id": {
          "name": "course_id",
          "type": "integer",
          "primaryKey": false,
          "notNull": false
        },
        "concept_name": {
          "name": "concept_name",
          "type": "text",
          "primaryKey": false,
          "notNull": true
        },
        "first_covered_at": {
          "name": "first_covered_at",
          "type": "text",
          "primaryKey": false,
          "notNull": false,
          "default": "CURRENT_TIMESTAMP"
        },
        "last_covered_at": {
          "name": "last_covered_at",
          "type": "text",
          "primaryKey": false,
          "notNull": false,
          "default": "CURRENT_TIMESTAMP"
        },
        "coverage_count": {
          "name": "coverage_count",
          "type": "integer",
          "primaryKey": false,
          "notNull": false,
          "default": 1
        },
        "mastery_level": {
          "name": "mastery_level",
          "type": "integer",
          "primaryKey": false,
          "notNull": false,
          "default": 1
        }
      },
      "indexes": {
        "concept_tracking_course_concept_idx": {
          "name": "concept_tracking_course_concept_idx",
          "columns": [
            {
              "expression": "course_id",
              "isExpression": false,
              "asc": true,
              "nulls": "last"
            },
            {
              "expression": "concept_name",
              "isExpression": false,
              "asc": true,
              "nulls": "last"
            }
          ],
          "isUnique": false,
          "concurrently": false,
          "method": "btree",
          "with": {}
        },
        "concept_tracking_user_id_idx": {
          "name": "concept_tracking_user_id_idx",
          "columns": [
            {
              "expression": "user_id",
              "isExpression": false,
              "asc": true,
              "nulls": "last"
            }
          ],
          "isUnique": false,
          "concurrently": false,
          "method": "btree",
          "with": {}
        }
      },
      "foreignKeys": {
        "concept_tracking_user_id_users_id_fk": {
          "name": "concept_tracking_user_id_users_id_fk",
          "tableFrom": "concept_tracking",
          "tableTo": "users",
          "columnsFrom": [
            "user_id"
          ],
          "columnsTo": [
            "id"
          ],
          "onDelete": "no action",
          "onUpdate": "no action"
        },
        "concept_tracking_course_id_courses_id_fk": {
          "name": "concept_tracking_course_id_courses_id_fk",
          "tableFrom": "concept_tracking",
          "tableTo": "courses",
          "columnsFrom": [
            "course_id"
          ],
          "columnsTo": [
            "id"
          ],
          "onDelete": "no action",
          "onUpdate": "no action"
        }
      },
      "compositePrimaryKeys": {},
      "uniqueConstraints": {},
      "policies": {},
      "checkConstraints": {},
      "isRLSEnabled": false
    },
    "public.courses": {
      "name": "courses",
      "schema": "",
      "columns": {
        "id": {
          "name": "id",
          "type": "serial",
          "primaryKey": true,
          "notNull": true
        },
        "user_id": {
          "name": "user_id",
          "type": "integer",
          "primaryKey": false,
          "notNull": false
        },
        "code": {
          "name": "code",
          "type": "varchar(10)",
          "primaryKey": false,
          "notNull": true
        },
        "name": {
          "name": "name",
          "type": "text",
          "primaryKey": false,
          "notNull": true
        },
        "program_of_study": {
          "name": "program_of_study",
          "type": "text",
          "primaryKey": false,
          "notNull": false
        },
        "icon": {
          "name": "icon",
          "type": "text",
          "primaryKey": false,
          "notNull": false,
          "default": "'Zap'"
        }
      },
      "indexes": {
        "courses_user_id_idx": {
          "name": "courses_user_id_idx",
          "columns": [
            {
              "expression": "user_id",
              "isExpression": false,
              "asc": true,
              "nulls": "last"
            }
          ],
          "isUnique": false,
          "concurrently": false,
          "method": "btree",
          "with": {}
        }
      },
      "foreignKeys": {
        "courses_user_id_users_id_fk": {
          "name": "courses_user_id_users_id_fk",
          "tableFrom": "courses",
          "tableTo": "users",
          "columnsFrom": [
            "user_id"
          ],
          "columnsTo": [
            "id"
          ],
          "onDelete": "no action",
          "onUpdate": "no action"
        }
      },
      "compositePrimaryKeys": {},
      "uniqueConstraints": {},
      "policies": {},
      "checkConstraints": {},
      "isRLSEnabled": false
    },
    "public.daily_feedback": {
      "name": "daily_feedback",
      "schema": "",
      "columns": {
        "id": {
          "name": "id",
          "type": "serial",
          "primaryKey": true,
          "notNull": true
        },
        "user_id": {
          "name": "user_id",
          "type": "integer",
          "primaryKey": false,
          "notNull": false
        },
        "feedback_date": {
          "name": "feedback_date",
          "type": "date",
          "primaryKey": false,
          "notNull": true
        },
        "completion_rating": {
          "name": "completion_rating",
          "type": "integer",
          "primaryKey": false,
          "notNull": false
        },
        "energy_level": {
          "name": "energy_level",
          "type": "integer",
          "primaryKey": false,
          "notNull": false
        },
        "notes": {
          "name": "notes",
          "type": "text",
          "primaryKey": false,
          "notNull": false
        },
        "created_at": {
          "name": "created_at",
          "type": "text",
          "primaryKey": false,
          "notNull": false,
          "default": "CURRENT_TIMESTAMP"
        }
      },
      "indexes": {
        "feedback_date_idx": {
          "name": "feedback_date_idx",
          "columns": [
            {
              "expression": "feedback_date",
              "isExpression": false,
              "asc": true,
              "nulls": "last"
            }
          ],
          "isUnique": false,
          "concurrently": false,
          "method": "btree",
          "with": {}
        },
        "feedback_user_date_idx": {
          "name": "feedback_user_date_idx",
          "columns": [
            {
              "expression": "user_id",
              "isExpression": false,
              "asc": true,
              "nulls": "last"
            },
            {
              "expression": "feedback_date",
              "isExpression": false,
              "asc": true,
              "nulls": "last"
            }
          ],
          "isUnique": false,
          "concurrently": false,
          "method": "btree",
          "with": {}
        }
      },
      "foreignKeys": {
        "daily_feedback_user_id_users_id_fk": {
          "name": "daily_feedback_user_id_users_id_fk",
          "tableFrom": "daily_feedback",
          "tableTo": "users",
          "columnsFrom": [
            "user_id"
          ],
          "columnsTo": [
            "id"
          ],
          "onDelete": "no action",
          "onUpdate": "no action"
        }
      },
      "compositePrimaryKeys": {},
      "uniqueConstraints": {},
      "policies": {},
      "checkConstraints": {},
      "isRLSEnabled": false
    },
    "public.daily_schedules": {
      "name": "daily_schedules",
      "schema": "",
      "columns": {
        "id": {
          "name": "id",
          "type": "serial",
          "primaryKey": true,
          "notNull": true
        },
        "user_id": {
          "name": "user_id",
          "type": "integer",
          "primaryKey": false,
          "notNull": false
        },
        "schedule_date": {
          "name": "schedule_date",
          "type": "date",
          "primaryKey": false,
          "notNull": true
        },
        "schedule_data": {
          "name": "schedule_data",
          "type": "text",
          "primaryKey": false,
          "notNull": true
        },
        "generated_at": {
          "name": "generated_at",
          "type": "text",
          "primaryKey": false,
          "notNull": false,
          "default": "CURRENT_TIMESTAMP"
        },
        "ai_reasoning": {
          "name": "ai_reasoning",
          "type": "text",
          "primaryKey": false,
          "notNull": false
        },
        "source": {
          "name": "source",
          "type": "text",
          "primaryKey": false,
          "notNull": false,
          "default": "'manual'"
        }
      },
      "indexes": {
        "schedules_date_idx": {
          "name": "schedules_date_idx",
          "columns": [
            {
              "expression": "schedule_date",
              "isExpression": false,
              "asc": true,
              "nulls": "last"
            }
          ],
          "isUnique": false,
          "concurrently": false,
          "method": "btree",
          "with": {}
        },
        "schedules_user_date_idx": {
          "name": "schedules_user_date_idx",
          "columns": [
            {
              "expression": "user_id",
              "isExpression": false,
              "asc": true,
              "nulls": "last"
            },
            {
              "expression": "schedule_date",
              "isExpression": false,
              "asc": true,
              "nulls": "last"
            }
          ],
          "isUnique": false,
          "concurrently": false,
          "method": "btree",
          "with": {}
        }
      },
      "foreignKeys": {
        "daily_schedules_user_id_users_id_fk": {
          "name": "daily_schedules_user_id_users_id_fk",
          "tableFrom": "daily_schedules",
          "tableTo": "users",
          "columnsFrom": [
            "user_id"
          ],
          "columnsTo": [
            "id"
          ],
          "onDelete": "no action",
          "onUpdate": "no action"
        }
      },
      "compositePrimaryKeys": {},
      "uniqueConstraints": {},
      "policies": {},
      "checkConstraints": {},
      "isRLSEnabled": false
    },
    "public.deadlines": {
      "name": "deadlines",
      "schema": "",
      "columns": {
        "id": {
          "name": "id",
          "type": "serial",
          "primaryKey": true,
          "notNull": true
        },
        "user_id": {
          "name": "user_id",
          "type": "integer",
          "primaryKey": false,
          "notNull": false
        },
        "title": {
          "name": "title",
          "type": "text",
          "primaryKey": false,
          "notNull": true
        },
        "type": {
          "name": "type",
          "type": "text",
          "primaryKey": false,
          "notNull": true
        },
        "course_id": {
          "name": "course_id",
          "type": "integer",
          "primaryKey": false,
          "notNull": false
        },
        "due_date": {
          "name": "due_date",
          "type": "date",
          "primaryKey": false,
          "notNull": true
        },
        "due_time": {
          "name": "due_time",
          "type": "text",
          "primaryKey": false,
          "notNull": false
        },
        "priority": {
          "name": "priority",
          "type": "integer",
          "primaryKey": false,
          "notNull": false,
          "default": 2
        },
        "description": {
          "name": "description",
          "type": "text",
          "primaryKey": false,
          "notNull": false
        },
        "created_at": {
          "name": "created_at",
          "type": "text",
          "primaryKey": false,
          "notNull": false,
          "default": "CURRENT_TIMESTAMP"
        }
      },
      "indexes": {
        "deadlines_course_date_idx": {
          "name": "deadlines_course_date_idx",
          "columns": [
            {
              "expression": "course_id",
              "isExpression": false,
              "asc": true,
              "nulls": "last"
            },
            {
              "expression": "due_date",
              "isExpression": false,
              "asc": true,
              "nulls": "last"
            }
          ],
          "isUnique": false,
          "concurrently": false,
          "method": "btree",
          "with": {}
        },
        "deadlines_date_idx": {
          "name": "deadlines_date_idx",
          "columns": [
            {
              "expression": "due_date",
              "isExpression": false,
              "asc": true,
              "nulls": "last"
            }
          ],
          "isUnique": false,
          "concurrently": false,
          "method": "btree",
          "with": {}
        },
        "deadlines_user_id_idx": {
          "name": "deadlines_user_id_idx",
          "columns": [
            {
              "expression": "user_id",
              "isExpression": false,
              "asc": true,
              "nulls": "last"
            }
          ],
          "isUnique": false,
          "concurrently": false,
          "method": "btree",
          "with": {}
        }
      },
      "foreignKeys": {
        "deadlines_user_id_users_id_fk": {
          "name": "deadlines_user_id_users_id_fk",
          "tableFrom": "deadlines",
          "tableTo": "users",
          "columnsFrom": [
            "user_id"
          ],
          "columnsTo": [
            "id"
          ],
          "onDelete": "no action",
          "onUpdate": "no action"
        },
        "deadlines_course_id_courses_id_fk": {
          "name": "deadlines_course_id_courses_id_fk",
          "tableFrom": "deadlines",
          "tableTo": "courses",
          "columnsFrom": [
            "course_id"
          ],
          "columnsTo": [
            "id"
          ],
          "onDelete": "no action",
          "onUpdate": "no action"
        }
      },
      "compositePrimaryKeys": {},
      "uniqueConstraints": {},
      "policies": {},
      "checkConstraints": {},
      "isRLSEnabled": false
    },
    "public.draft_schedules": {
      "name": "draft_schedules",
      "schema": "",
      "columns": {
        "id": {
          "name": "id",
          "type": "serial",
          "primaryKey": true,
          "notNull": true
        },
        "user_id": {
          "name": "user_id",
          "type": "integer",
          "primaryKey": false,
          "notNull": false
        },
        "schedule_date": {
          "name": "schedule_date",
          "type": "date",
          "primaryKey": false,
          "notNull": true
        },
        "schedule_data": {
          "name": "schedule_data",
          "type": "text",
          "primaryKey": false,
          "notNull": true
        },
        "source": {
          "name": "source",
          "type": "text",
          "primaryKey": false,
          "notNull": true
        },
        "chat_prompt": {
          "name": "chat_prompt",
          "type": "text",
          "primaryKey": false,
          "notNull": false
        },
        "ai_reasoning": {
          "name": "ai_reasoning",
          "type": "text",
          "primaryKey": false,
          "notNull": false
        },
        "is_finalized": {
          "name": "is_finalized",
          "type": "boolean",
          "primaryKey": false,
          "notNull": false,
          "default": false
        },
        "created_at": {
          "name": "created_at",
          "type": "text",
          "primaryKey": false,
          "notNull": false,
          "default": "CURRENT_TIMESTAMP"
        }
      },
      "indexes": {
        "draft_schedules_date_idx": {
          "name": "draft_schedules_date_idx",
          "columns": [
            {
              "expression": "schedule_date",
              "isExpression": false,
              "asc": true,
              "nulls": "last"
            }
          ],
          "isUnique": false,
          "concurrently": false,
          "method": "btree",
          "with": {}
        },
        "draft_schedules_user_date_idx": {
          "name": "draft_schedules_user_date_idx",
          "columns": [
            {
              "expression": "user_id",
              "isExpression": false,
              "asc": true,
              "nulls": "last"
            }
          ],
          "isUnique": false,
          "concurrently": false,
          "method": "btree",
          "with": {}
        }
      },
      "foreignKeys": {
        "draft_schedules_user_id_users_id_fk": {
          "name": "draft_schedules_user_id_users_id_fk",
          "tableFrom": "draft_schedules",
          "tableTo": "users",
          "columnsFrom": [
            "user_id"
          ],
          "columnsTo": [
            "id"
          ],
          "onDelete": "no action",
          "onUpdate": "no action"
        }
      },
      "compositePrimaryKeys": {},
      "uniqueConstraints": {},
      "policies": {},
      "checkConstraints": {},
      "isRLSEnabled": false
    },
    "public.mission_feedback": {
      "name": "mission_feedback",
      "schema": "",
      "columns": {
        "id": {
          "name": "id",
          "type": "serial",
          "primaryKey": true,
          "notNull": true
        },
        "mission_id": {
          "name": "mission_id",
          "type": "integer",
          "primaryKey": false,
          "notNull": true
        },
        "difficulty": {
          "name": "difficulty",
          "type": "integer",
          "primaryKey": false,
          "notNull": false
        },
        "time_accuracy": {
          "name": "time_accuracy",
          "type": "integer",
          "primaryKey": false,
          "notNull": false
        },
        "notes": {
          "name": "notes",
          "type": "text",
          "primaryKey": false,
          "notNull": false
        },
        "created_at": {
          "name": "created_at",
          "type": "text",
          "primaryKey": false,
          "notNull": false,
          "default": "CURRENT_TIMESTAMP"
        }
      },
      "indexes": {
        "mission_feedback_mission_id_idx": {
          "name": "mission_feedback_mission_id_idx",
          "columns": [
            {
              "expression": "mission_id",
              "isExpression": false,
              "asc": true,
              "nulls": "last"
            }
          ],
          "isUnique": false,
          "concurrently": false,
          "method": "btree",
          "with": {}
        }
      },
      "foreignKeys": {
        "mission_feedback_mission_id_missions_id_fk": {
          "name": "mission_feedback_mission_id_missions_id_fk",
          "tableFrom": "mission_feedback",
          "tableTo": "missions",
          "columnsFrom": [
            "mission_id"
          ],
          "columnsTo": [
            "id"
          ],
          "onDelete": "no action",
          "onUpdate": "no action"
        }
      },
      "compositePrimaryKeys": {},
      "uniqueConstraints": {},
      "policies": {},
      "checkConstraints": {},
      "isRLSEnabled": false
    },
    "public.missions": {
      "name": "missions",
      "schema": "",
      "columns": {
        "id": {
          "name": "id",
          "type": "serial",
          "primaryKey": true,
          "notNull": true
        },
        "user_id": {
          "name": "user_id",
          "type": "integer",
          "primaryKey": false,
          "notNull": false
        },
        "course_id": {
          "name": "course_id",
          "type": "integer",
          "primaryKey": false,
          "notNull": true
        },
        "title": {
          "name": "title",
          "type": "text",
          "primaryKey": false,
          "notNull": true
        },
        "description": {
          "name": "description",
          "type": "text",
          "primaryKey": false,
          "notNull": true
        },
        "proof_requirement": {
          "name": "proof_requirement",
          "type": "text",
          "primaryKey": false,
          "notNull": true
        },
        "mission_date": {
          "name": "mission_date",
          "type": "date",
          "primaryKey": false,
          "notNull": true
        },
        "status": {
          "name": "status",
          "type": "text",
          "primaryKey": false,
          "notNull": false,
          "default": "'pending'"
        },
        "created_at": {
          "name": "created_at",
          "type": "text",
          "primaryKey": false,
          "notNull": false,
          "default": "CURRENT_TIMESTAMP"
        }
      },
      "indexes": {
        "missions_course_id_idx": {
          "name": "missions_course_id_idx",
          "columns": [
            {
              "expression": "course_id",
              "isExpression": false,
              "asc": true,
              "nulls": "last"
            }
          ],
          "isUnique": false,
          "concurrently": false,
          "method": "btree",
          "with": {}
        },
        "missions_date_idx": {
          "name": "missions_date_idx",
          "columns": [
            {
              "expression": "mission_date",
              "isExpression": false,
              "asc": true,
              "nulls": "last"
            }
          ],
          "isUnique": false,
          "concurrently": false,
          "method": "btree",
          "with": {}
        },
        "missions_user_id_idx": {
          "name": "missions_user_id_idx",
          "columns": [
            {
              "expression": "user_id",
              "isExpression": false,
              "asc": true,
              "nulls": "last"
            }
          ],
          "isUnique": false,
          "concurrently": false,
          "method": "btree",
          "with": {}
        }
      },
      "foreignKeys": {
        "missions_user_id_users_id_fk": {
          "name": "missions_user_id_users_id_fk",
          "tableFrom": "missions",
          "tableTo": "users",
          "columnsFrom": [
            "user_id"
          ],
          "columnsTo": [
            "id"
          ],
          "onDelete": "no action",
          "onUpdate": "no action"
        },
        "missions_course_id_courses_id_fk": {
          "name": "missions_course_id_courses_id_fk",
          "tableFrom": "missions",
          "tableTo": "courses",
          "columnsFrom": [
            "course_id"
          ],
          "columnsTo": [
            "id"
          ],
          "onDelete": "no action",
          "onUpdate": "no action"
        }
      },
      "compositePrimaryKeys": {},
      "uniqueConstraints": {},
      "policies": {},
      "checkConstraints": {},
      "isRLSEnabled": false
    },
    "public.notifications": {
      "name": "notifications",
      "schema": "",
      "columns": {
        "id": {
          "name": "id",
          "type": "serial",
          "primaryKey": true,
          "notNull": true
        },
        "user_id": {
          "name": "user_id",
          "type": "integer",
          "primaryKey": false,
          "notNull": false
        },
        "type": {
          "name": "type",
          "type": "text",
          "primaryKey": false,
          "notNull": true
        },
        "title": {
          "name": "title",
          "type": "text",
          "primaryKey": false,
          "notNull": true
        },
        "message": {
          "name": "message",
          "type": "text",
          "primaryKey": false,
          "notNull": true
        },
        "mission_id": {
          "name": "mission_id",
          "type": "integer",
          "primaryKey": false,
          "notNull": false
        },
        "created_at": {
          "name": "created_at",
          "type": "text",
          "primaryKey": false,
          "notNull": false,
          "default": "CURRENT_TIMESTAMP"
        }
      },
      "indexes": {
        "notifications_created_at_idx": {
          "name": "notifications_created_at_idx",
          "columns": [
            {
              "expression": "created_at",
              "isExpression": false,
              "asc": true,
              "nulls": "last"
            }
          ],
          "isUnique": false,
          "concurrently": false,
          "method": "btree",
          "with": {}
        },
        "notifications_user_id_idx": {
          "name": "notifications_user_id_idx",
          "columns": [
            {
              "expression": "user_id",
              "isExpression": false,
              "asc": true,
              "nulls": "last"
            }
          ],
          "isUnique": false,
          "concurrently": false,
          "method": "btree",
          "with": {}
        }
      },
      "foreignKeys": {
        "notifications_user_id_users_id_fk": {
          "name": "notifications_user_id_users_id_fk",
          "tableFrom": "notifications",
          "tableTo": "users",
          "columnsFrom": [
            "user_id"
          ],
          "columnsTo": [
            "id"
          ],
          "onDelete": "no action",
          "onUpdate": "no action"
        }
      },
      "compositePrimaryKeys": {},
      "uniqueConstraints": {},
      "policies": {},
      "checkConstraints": {},
      "isRLSEnabled": false
    },
    "public.proofs": {
      "name": "proofs",
      "schema": "",
      "columns": {
        "id": {
          "name": "id",
          "type": "serial",
          "primaryKey": true,
          "notNull": true
        },
        "mission_id": {
          "name": "mission_id",
          "type": "integer",
          "primaryKey": false,
          "notNull": true
        },
        "file_name": {
          "name": "file_name",
          "type": "text",
          "primaryKey": false,
          "notNull": true
        },
        "file_size": {
          "name": "file_size",
          "type": "integer",
          "primaryKey": false,
          "notNull": false
        },
        "uploaded_at": {
          "name": "uploaded_at",
          "type": "text",
          "primaryKey": false,
          "notNull": false,
          "default": "CURRENT_TIMESTAMP"
        }
      },
      "indexes": {
        "proofs_mission_id_idx": {
          "name": "proofs_mission_id_idx",
          "columns": [
            {
              "expression": "mission_id",
              "isExpression": false,
              "asc": true,
              "nulls": "last"
            }
          ],
          "isUnique": false,
          "concurrently": false,
          "method": "btree",
          "with": {}
        }
      },
      "foreignKeys": {
        "proofs_mission_id_missions_id_fk": {
          "name": "proofs_mission_id_missions_id_fk",
          "tableFrom": "proofs",
          "tableTo": "missions",
          "columnsFrom": [
            "mission_id"
          ],
          "columnsTo": [
            "id"
          ],
          "onDelete": "no action",
          "onUpdate": "no action"
        }
      },
      "compositePrimaryKeys": {},
      "uniqueConstraints": {},
      "policies": {},
      "checkConstraints": {},
      "isRLSEnabled": false
    },
    "public.schedule_block_feedback": {
      "name": "schedule_block_feedback",
      "schema": "",
      "columns": {
        "id": {
          "name": "id",
          "type": "serial",
          "primaryKey": true,
          "notNull": true
        },
        "user_id": {
          "name": "user_id",
          "type": "integer",
          "primaryKey": false,
          "notNull": false
        },
        "schedule_date": {
          "name": "schedule_date",
          "type": "date",
          "primaryKey": false,
          "notNull": true
        },
        "block_start_time": {
          "name": "block_start_time",
          "type": "text",
          "primaryKey": false,
          "notNull": true
        },
        "completed": {
          "name": "completed",
          "type": "boolean",
          "primaryKey": false,
          "notNull": false,
          "default": false
        },
        "skipped": {
          "name": "skipped",
          "type": "boolean",
          "primaryKey": false,
          "notNull": false,
          "default": false
        },
        "skip_reason": {
          "name": "skip_reason",
          "type": "text",
          "primaryKey": false,
          "notNull": false
        },
        "custom_skip_reason": {
          "name": "custom_skip_reason",
          "type": "text",
          "primaryKey": false,
          "notNull": false
        },
        "energy_level": {
          "name": "energy_level",
          "type": "integer",
          "primaryKey": false,
          "notNull": false
        },
        "accuracy": {
          "name": "accuracy",
          "type": "text",
          "primaryKey": false,
          "notNull": false
        },
        "difficulty": {
          "name": "difficulty",
          "type": "integer",
          "primaryKey": false,
          "notNull": false
        },
        "actual_time_spent": {
          "name": "actual_time_spent",
          "type": "integer",
          "primaryKey": false,
          "notNull": false
        },
        "topics_covered": {
          "name": "topics_covered",
          "type": "text",
          "primaryKey": false,
          "notNull": false
        },
        "comments": {
          "name": "comments",
          "type": "text",
          "primaryKey": false,
          "notNull": false
        },
        "created_at": {
          "name": "created_at",
          "type": "text",
          "primaryKey": false,
          "notNull": false,
          "default": "CURRENT_TIMESTAMP"
        },
        "updated_at": {
          "name": "updated_at",
          "type": "text",
          "primaryKey": false,
          "notNull": false,
          "default": "CURRENT_TIMESTAMP"
        }
      },
      "indexes": {
        "block_feedback_date_time_idx": {
          "name": "block_feedback_date_time_idx",
          "columns": [
            {
              "expression": "schedule_date",
              "isExpression": false,
              "asc": true,
              "nulls": "last"
            },
            {
              "expression": "block_start_time",
              "isExpression": false,
              "asc": true,
              "nulls": "last"
            }
          ],
          "isUnique": false,
          "concurrently": false,
          "method": "btree",
          "with": {}
        },
        "block_feedback_date_idx": {
          "name": "block_feedback_date_idx",
          "columns": [
            {
              "expression": "schedule_date",
              "isExpression": false,
              "asc": true,
              "nulls": "last"
            }
          ],
          "isUnique": false,
          "concurrently": false,
          "method": "btree",
          "with": {}
        },
        "block_feedback_user_id_idx": {
          "name": "block_feedback_user_id_idx",
          "columns": [
            {
              "expression": "user_id",
              "isExpression": false,
              "asc": true,
              "nulls": "last"
            }
          ],
          "isUnique": false,
          "concurrently": false,
          "method": "btree",
          "with": {}
        }
      },
      "foreignKeys": {
        "schedule_block_feedback_user_id_users_id_fk": {
          "name": "schedule_block_feedback_user_id_users_id_fk",
          "tableFrom": "schedule_block_feedback",
          "tableTo": "users",
          "columnsFrom": [
            "user_id"
          ],
          "columnsTo": [
            "id"
          ],
          "onDelete": "no action",
          "onUpdate": "no action"
        }
      },
      "compositePrimaryKeys": {},
      "uniqueConstraints": {},
      "policies": {},
      "checkConstraints": {},
      "isRLSEnabled": false
    },
    "public.schedule_drift_events": {
      "name": "schedule_drift_events",
      "schema": "",
      "columns": {
        "id": {
          "name": "id",
          "type": "serial",
          "primaryKey": true,
          "notNull": true
        },
        "user_id": {
          "name": "user_id",
          "type": "integer",
          "primaryKey": false,
          "notNull": false
        },
        "schedule_date": {
          "name": "schedule_date",
          "type": "date",
          "primaryKey": false,
          "notNull": true
        },
        "block_start_time": {
          "name": "block_start_time",
          "type": "text",
          "primaryKey": false,
          "notNull": true
        },
        "block_title": {
          "name": "block_title",
          "type": "text",
          "primaryKey": false,
          "notNull": true
        },
        "planned_duration": {
          "name": "planned_duration",
          "type": "integer",
          "primaryKey": false,
          "notNull": true
        },
        "actual_duration": {
          "name": "actual_duration",
          "type": "integer",
          "primaryKey": false,
          "notNull": true
        },
        "drift_minutes": {
          "name": "drift_minutes",
          "type": "integer",
          "primaryKey": false,
          "notNull": true
        },
        "cumulative_drift": {
          "name": "cumulative_drift",
          "type": "integer",
          "primaryKey": false,
          "notNull": true
        },
        "affected_blocks_count": {
          "name": "affected_blocks_count",
          "type": "integer",
          "primaryKey": false,
          "notNull": true
        },
        "user_choice": {
          "name": "user_choice",
          "type": "text",
          "primaryKey": false,
          "notNull": false
        },
        "ai_reschedule_suggestion": {
          "name": "ai_reschedule_suggestion",
          "type": "text",
          "primaryKey": false,
          "notNull": false
        },
        "resolved": {
          "name": "resolved",
          "type": "boolean",
          "primaryKey": false,
          "notNull": false,
          "default": false
        },
        "created_at": {
          "name": "created_at",
          "type": "text",
          "primaryKey": false,
          "notNull": false,
          "default": "CURRENT_TIMESTAMP"
        },
        "resolved_at": {
          "name": "resolved_at",
          "type": "text",
          "primaryKey": false,
          "notNull": false
        }
      },
      "indexes": {
        "drift_events_date_idx": {
          "name": "drift_events_date_idx",
          "columns": [
            {
              "expression": "schedule_date",
              "isExpression": false,
              "asc": true,
              "nulls": "last"
            }
          ],
          "isUnique": false,
          "concurrently": false,
          "method": "btree",
          "with": {}
        },
        "drift_events_unresolved_idx": {
          "name": "drift_events_unresolved_idx",
          "columns": [
            {
              "expression": "schedule_date",
              "isExpression": false,
              "asc": true,
              "nulls": "last"
            },
            {
              "expression": "resolved",
              "isExpression": false,
              "asc": true,
              "nulls": "last"
            }
          ],
          "isUnique": false,
          "concurrently": false,
          "method": "btree",
          "with": {}
        },
        "drift_events_user_id_idx": {
          "name": "drift_events_user_id_idx",
          "columns": [
            {
              "expression": "user_id",
              "isExpression": false,
              "asc": true,
              "nulls": "last"
            }
          ],
          "isUnique": false,
          "concurrently": false,
          "method": "btree",
          "with": {}
        }
      },
      "foreignKeys": {
        "schedule_drift_events_user_id_users_id_fk": {
          "name": "schedule_drift_events_user_id_users_id_fk",
          "tableFrom": "schedule_drift_events",
          "tableTo": "users",
          "columnsFrom": [
            "user_id"
          ],
          "columnsTo": [
            "id"
          ],
          "onDelete": "no action",
          "onUpdate": "no action"
        }
      },
      "compositePrimaryKeys": {},
      "uniqueConstraints": {},
      "policies": {},
      "checkConstraints": {},
      "isRLSEnabled": false
    },
    "public.settings": {
      "name": "settings",
      "schema": "",
      "columns": {
        "id": {
          "name": "id",
          "type": "serial",
          "primaryKey": true,
          "notNull": true
        },
        "user_id": {
          "name": "user_id",
          "type": "integer",
          "primaryKey": false,
          "notNull": false
        },
        "key": {
          "name": "key",
          "type": "varchar(50)",
          "primaryKey": false,
          "notNull": true
        },
        "value": {
          "name": "value",
          "type": "text",
          "primaryKey": false,
          "notNull": true
        },
        "updated_at": {
          "name": "updated_at",
          "type": "text",
          "primaryKey": false,
          "notNull": false,
          "default": "CURRENT_TIMESTAMP"
        }
      },
      "indexes": {
        "settings_user_key_idx": {
          "name": "settings_user_key_idx",
          "columns": [
            {
              "expression": "user_id",
              "isExpression": false,
              "asc": true,
              "nulls": "last"
            },
            {
              "expression": "key",
              "isExpression": false,
              "asc": true,
              "nulls": "last"
            }
          ],
          "isUnique": false,
          "concurrently": false,
          "method": "btree",
          "with": {}
        }
      },
      "foreignKeys": {
        "settings_user_id_users_id_fk": {
          "name": "settings_user_id_users_id_fk",
          "tableFrom": "settings",
          "tableTo": "users",
          "columnsFrom": [
            "user_id"
          ],
          "columnsTo": [
            "id"
          ],
          "onDelete": "no action",
          "onUpdate": "no action"
        }
      },
      "compositePrimaryKeys": {},
      "uniqueConstraints": {},
      "policies": {},
      "checkConstraints": {},
      "isRLSEnabled": false
    },
    "public.uploaded_files": {
      "name": "uploaded_files",
      "schema": "",
      "columns": {
        "id": {
          "name": "id",
          "type": "serial",
          "primaryKey": true,
          "notNull": true
        },
        "course_code": {
          "name": "course_code",
          "type": "varchar(10)",
          "primaryKey": false,
          "notNull": true
        },
        "file_name": {
          "name": "file_name",
          "type": "text",
          "primaryKey": false,
          "notNull": true
        },
        "original_name": {
          "name": "original_name",
          "type": "text",
          "primaryKey": false,
          "notNull": true
        },
        "status": {
          "name": "status",
          "type": "varchar(20)",
          "primaryKey": false,
          "notNull": false,
          "default": "'pending'"
        },
        "extracted_chunks": {
          "name": "extracted_chunks",
          "type": "integer",
          "primaryKey": false,
          "notNull": false,
          "default": 0
        },
        "concepts": {
          "name": "concepts",
          "type": "text",
          "primaryKey": false,
          "notNull": false
        },
        "summary": {
          "name": "summary",
          "type": "text",
          "primaryKey": false,
          "notNull": false
        },
        "error": {
          "name": "error",
          "type": "text",
          "primaryKey": false,
          "notNull": false
        },
        "uploaded_at": {
          "name": "uploaded_at",
          "type": "text",
          "primaryKey": false,
          "notNull": false,
          "default": "CURRENT_TIMESTAMP"
        },
        "extracted_at": {
          "name": "extracted_at",
          "type": "text",
          "primaryKey": false,
          "notNull": false
        }
      },
      "indexes": {
        "uploaded_files_course_code_idx": {
          "name": "uploaded_files_course_code_idx",
          "columns": [
            {
              "expression": "course_code",
              "isExpression": false,
              "asc": true,
              "nulls": "last"
            }
          ],
          "isUnique": false,
          "concurrently": false,
          "method": "btree",
          "with": {}
        },
        "uploaded_files_status_idx": {
          "name": "uploaded_files_status_idx",
          "columns": [
            {
              "expression": "status",
              "isExpression": false,
              "asc": true,
              "nulls": "last"
            }
          ],
          "isUnique": false,
          "concurrently": false,
          "method": "btree",
          "with": {}
        }
      },
      "foreignKeys": {},
      "compositePrimaryKeys": {},
      "uniqueConstraints": {},
      "policies": {},
      "checkConstraints": {},
      "isRLSEnabled": false
    },
    "public.user_patterns": {
      "name": "user_patterns",
      "schema": "",
      "columns": {
        "id": {
          "name": "id",
          "type": "serial",
          "primaryKey": true,
          "notNull": true
        },
        "user_id": {
          "name": "user_id",
          "type": "integer",
          "primaryKey": false,
          "notNull": false
        },
        "pattern_type": {
          "name": "pattern_type",
          "type": "varchar(100)",
          "primaryKey": false,
          "notNull": true
        },
        "pattern_value": {
          "name": "pattern_value",
          "type": "text",
          "primaryKey": false,
          "notNull": true
        },
        "confidence": {
          "name": "confidence",
          "type": "text",
          "primaryKey": false,
          "notNull": false,
          "default": "'0.5'"
        },
        "updated_at": {
          "name": "updated_at",
          "type": "text",
          "primaryKey": false,
          "notNull": false,
          "default": "CURRENT_TIMESTAMP"
        }
      },
      "indexes": {
        "user_patterns_user_pattern_idx": {
          "name": "user_patterns_user_pattern_idx",
          "columns": [
            {
              "expression": "user_id",
              "isExpression": false,
              "asc": true,
              "nulls": "last"
            },
            {
              "expression": "pattern_type",
              "isExpression": false,
              "asc": true,
              "nulls": "last"
            }
          ],
          "isUnique": false,
          "concurrently": false,
          "method": "btree",
          "with": {}
        }
      },
      "foreignKeys": {
        "user_patterns_user_id_users_id_fk": {
          "name": "user_patterns_user_id_users_id_fk",
          "tableFrom": "user_patterns",
          "tableTo": "users",
          "columnsFrom": [
            "user_id"
          ],
          "columnsTo": [
            "id"
          ],
          "onDelete": "no action",
          "onUpdate": "no action"
        }
      },
      "compositePrimaryKeys": {},
      "uniqueConstraints": {},
      "policies": {},
      "checkConstraints": {},
      "isRLSEnabled": false
    },
    "public.user_preferences": {
      "name": "user_preferences",
      "schema": "",
      "columns": {
        "id": {
          "name": "id",
          "type": "serial",
          "primaryKey": true,
          "notNull": true
        },
        "user_id": {
          "name": "user_id",
          "type": "integer",
          "primaryKey": false,
          "notNull": false
        },
        "wake_time": {
          "name": "wake_time",
          "type": "text",
          "primaryKey": false,
          "notNull": false,
          "default": "'06:00'"
        },
        "sleep_time": {
          "name": "sleep_time",
          "type": "text",
          "primaryKey": false,
          "notNull": false,
          "default": "'22:00'"
        },
        "target_work_hours": {
          "name": "target_work_hours",
          "type": "integer",
          "primaryKey": false,
          "notNull": false,
          "default": 6
        },
        "target_free_hours": {
          "name": "target_free_hours",
          "type": "integer",
          "primaryKey": false,
          "notNull": false,
          "default": 4
        },
        "target_other_hours": {
          "name": "target_other_hours",
          "type": "integer",
          "primaryKey": false,
          "notNull": false,
          "default": 4
        },
        "consecutive_study_limit": {
          "name": "consecutive_study_limit",
          "type": "integer",
          "primaryKey": false,
          "notNull": false,
          "default": 90
        },
        "personal_goals": {
          "name": "personal_goals",
          "type": "text",
          "primaryKey": false,
          "notNull": false
        },
        "schedule_generation_time": {
          "name": "schedule_generation_time",
          "type": "text",
          "primaryKey": false,
          "notNull": false,
          "default": "'06:00'"
        },
        "evening_prompt_time": {
          "name": "evening_prompt_time",
          "type": "text",
          "primaryKey": false,
          "notNull": false,
          "default": "'18:00'"
        },
        "activity_notifications": {
          "name": "activity_notifications",
          "type": "boolean",
          "primaryKey": false,
          "notNull": false,
          "default": true
        },
        "notification_sound": {
          "name": "notification_sound",
          "type": "boolean",
          "primaryKey": false,
          "notNull": false,
          "default": true
        },
        "selected_sound": {
          "name": "selected_sound",
          "type": "text",
          "primaryKey": false,
          "notNull": false,
          "default": "'chime'"
        },
        "sound_volume": {
          "name": "sound_volume",
          "type": "integer",
          "primaryKey": false,
          "notNull": false,
          "default": 70
        },
        "updated_at": {
          "name": "updated_at",
          "type": "text",
          "primaryKey": false,
          "notNull": false,
          "default": "CURRENT_TIMESTAMP"
        }
      },
      "indexes": {},
      "foreignKeys": {
        "user_preferences_user_id_users_id_fk": {
          "name": "user_preferences_user_id_users_id_fk",
          "tableFrom": "user_preferences",
          "tableTo": "users",
          "columnsFrom": [
            "user_id"
          ],
          "columnsTo": [
            "id"
          ],
          "onDelete": "no action",
          "onUpdate": "no action"
        }
      },
      "compositePrimaryKeys": {},
      "uniqueConstraints": {
        "user_preferences_user_id_unique": {
          "name": "user_preferences_user_id_unique",
          "nullsNotDistinct": false,
          "columns": [
            "user_id"
          ]
        }
      },
      "policies": {},
      "checkConstraints": {},
      "isRLSEnabled": false
    },
    "public.users": {
      "name": "users",
      "schema": "",
      "columns": {
        "id": {
          "name": "id",
          "type": "serial",
          "primaryKey": true,
          "notNull": true
        },
        "email": {
          "name": "email",
          "type": "varchar(255)",
          "primaryKey": false,
          "notNull": true
        },
        "password": {
          "name": "password",
          "type": "text",
          "primaryKey": false,
          "notNull": true
        },
        "name": {
          "name": "name",
          "type": "text",
          "primaryKey": false,
          "notNull": true
        },
        "has_created_first_schedule": {
          "name": "has_created_first_schedule",
          "type": "boolean",
          "primaryKey": false,
          "notNull": false,
          "default": false
        },
        "created_at": {
          "name": "created_at",
          "type": "text",
          "primaryKey": false,
          "notNull": false,
          "default": "CURRENT_TIMESTAMP"
        }
      },
      "indexes": {},
      "foreignKeys": {},
      "compositePrimaryKeys": {},
      "uniqueConstraints": {
        "users_email_unique": {
          "name": "users_email_unique",
          "nullsNotDistinct": false,
          "columns": [
            "email"
          ]
        }
      },
      "policies": {},
      "checkConstraints": {},
      "isRLSEnabled": false
    }
  },
  "enums": {},
  "schemas": {},
  "sequences": {},
  "roles": {},
  "policies": {},
  "views": {},
  "_meta": {
    "columns": {},
    "schemas": {},
    "tables": {}
  }
}